apimatic_open_api_sdk-1.0.0.dist-info/licenses/LICENSE
openaiapi/__init__.py
openaiapi/api_helper.py
openaiapi/configuration.py
openaiapi/openaiapi_client.py
openaiapi/controllers/__init__.py
openaiapi/controllers/base_controller.py
openaiapi/controllers/batch_api_requests_controller.py
openaiapi/controllers/batches_controller.py
openaiapi/controllers/build_a_simple_faq_system_embeddings_api_controller.py
openaiapi/controllers/chat_completions_controller.py
openaiapi/controllers/embeddings_controller.py
openaiapi/controllers/files_controller.py
openaiapi/controllers/fine_tuning_controller.py
openaiapi/controllers/function_calling_chat_completions_api_controller.py
openaiapi/controllers/image_generation_controller.py
openaiapi/controllers/messages_controller.py
openaiapi/controllers/models_controller.py
openaiapi/controllers/moderations_controller.py
openaiapi/controllers/open_ai_assistants_api_beta_controller.py
openaiapi/controllers/predicted_outputs_controller.py
openaiapi/controllers/reasoning_controller.py
openaiapi/controllers/runs_controller.py
openaiapi/controllers/structured_outputs_controller.py
openaiapi/controllers/text_generation_chat_completions_api_controller.py
openaiapi/controllers/threads_controller.py
openaiapi/controllers/vector_store_controller.py
openaiapi/controllers/vector_store_files_controller.py
openaiapi/exceptions/__init__.py
openaiapi/exceptions/api_exception.py
openaiapi/http/__init__.py
openaiapi/http/http_call_back.py
openaiapi/http/http_method_enum.py
openaiapi/http/http_request.py
openaiapi/http/http_response.py
openaiapi/http/auth/__init__.py
openaiapi/http/auth/o_auth_2.py
openaiapi/models/__init__.py
openaiapi/models/categories.py
openaiapi/models/category_scores.py
openaiapi/models/chat_completions.py
openaiapi/models/chat_completions_reasoning_o_1.py
openaiapi/models/chat_completions_reasoning_o_1_mini.py
openaiapi/models/chat_completions_reasoning_o_1_mini_request.py
openaiapi/models/chat_completions_reasoning_o_1_request.py
openaiapi/models/chat_completions_reasoning_o_3_mini.py
apimatic_open_api_sdk-1.0.0.dist-info/METADATA
apimatic_open_api_sdk-1.0.0.dist-info/WHEEL
apimatic_open_api_sdk-1.0.0.dist-info/top_level.txt
apimatic_open_api_sdk-1.0.0.dist-info/RECORD
